blbt/__init__.py
blbt/__main__.py
blbt-1.0.5.dist-info/METADATA
blbt-1.0.5.dist-info/WHEEL
blbt-1.0.5.dist-info/entry_points.txt
blbt-1.0.5.dist-info/top_level.txt
blbt-1.0.5.dist-info/RECORD
