Metadata-Version: 2.4
Name: blbt
Version: 1.0.5
Summary: A command-line utility to calculate the real-world gift card value of your Makerworld boosts across different regional stores.
Home-page: https://github.com/thefilipcom4607/blbt
Author: thefilipcom4607
Author-email: thefilipcom4607 <fm@thefilip.com>
License: MIT
Project-URL: Homepage, https://github.com/thefilipcom4607/blbt
Requires-Python: >=3.8
Requires-Dist: requests>=2.31.0
Requires-Dist: colorama>=0.4.6
